{
	"configurations" : 
	[
		{
			"directories" : 
			[
				{
					"build" : ".",
					"jsonFile" : "directory-.-Debug-d0094a50bb2071803777.json",
					"minimumCMakeVersion" : 
					{
						"string" : "3.28"
					},
					"projectIndex" : 0,
					"source" : ".",
					"targetIndexes" : 
					[
						0
					]
				}
			],
			"name" : "Debug",
			"projects" : 
			[
				{
					"directoryIndexes" : 
					[
						0
					],
					"name" : "Pract8",
					"targetIndexes" : 
					[
						0
					]
				}
			],
			"targets" : 
			[
				{
					"directoryIndex" : 0,
					"id" : "Pract8::@6890427a1f51a3e7e1df",
					"jsonFile" : "target-Pract8-Debug-65ae53c5be2e9a166663.json",
					"name" : "Pract8",
					"projectIndex" : 0
				}
			]
		}
	],
	"kind" : "codemodel",
	"paths" : 
	{
		"build" : "C:/Users/broGideon/CLionProjects/Pract8/cmake-build-debug",
		"source" : "C:/Users/broGideon/CLionProjects/Pract8"
	},
	"version" : 
	{
		"major" : 2,
		"minor" : 6
	}
}
